{
  "generated_at": "2026-04-04T20:00:05.622406-04:00",
  "window": {
    "start": "2026-04-04T19:00:05.622406-04:00",
    "end": "2026-04-04T20:00:05.622406-04:00"
  },
  "sites": {
    "perrenguematogrosso": [
      {
        "title": "Recorde mundial: barra de chocolate de 222 metros é feita em Bariloche durante festival; Veja vídeo",
        "link": "https://perrenguematogrosso.com/recorde-mundial-barra-de-chocolate-de-222-metros-e-feita-em-bariloche-durante-festival-veja-video/",
        "author": "Karolina silva",
        "author_id": 290,
        "published": "2026-04-04T19:30:00-04:00",
        "categories": [
          "Notícias"
        ],
        "category_ids": [
          5
        ]
      },
      {
        "title": "‘Peixe Santo’ esgota após venda de 45 toneladas e alta procura na Semana Santa em Cuiabá",
        "link": "https://perrenguematogrosso.com/peixe-santo-esgota-venda-45-toneladas-semana-santa-cuiaba/",
        "author": "Mhylenna",
        "author_id": 279,
        "published": "2026-04-04T19:40:00-04:00",
        "categories": [
          "Vovô de Olho"
        ],
        "category_ids": [
          16
        ]
      }
    ],
    "afolhalivre": [],
    "omatogrossense": [
      {
        "title": "Bariloche quebra recorde mundial com barra de chocolate de 222 metros no Festival Nacional do Chocolate; Veja vídeo",
        "link": "https://omatogrossense.com/bariloche-na-argentina-entrou/",
        "author": "Karolina Coelho da Silva",
        "author_id": 22,
        "published": "2026-04-04T19:32:00-04:00",
        "categories": [
          "MT Notícias"
        ],
        "category_ids": [
          20
        ]
      }
    ],
    "portalnortemt": [],
    "portalpantanalmt": [],
    "roonoticias": []
  },
  "menu_category_ids": {
    "perrenguematogrosso": [
      4,
      5,
      16,
      509,
      510
    ],
    "afolhalivre": [
      5,
      7,
      20,
      973,
      3032
    ],
    "omatogrossense": [
      5,
      7,
      20,
      973
    ],
    "portalnortemt": [
      5,
      7,
      20,
      973,
      3030
    ],
    "portalpantanalmt": [
      5,
      7,
      20,
      973,
      3105
    ],
    "roonoticias": [
      5,
      7,
      20,
      973,
      3118
    ]
  }
}