{
  "generated_at": "2026-04-08T15:00:05.529321-04:00",
  "window": {
    "start": "2026-04-08T14:00:05.529321-04:00",
    "end": "2026-04-08T15:00:05.529321-04:00"
  },
  "sites": {
    "perrenguematogrosso": [
      {
        "title": "Megaoperação derruba esquema bilionário de jogos ilegais e prende 55 pessoas, incluindo vereadores; Veja vídeo",
        "link": "https://perrenguematogrosso.com/esquema-bilionario-foi-desarticulado/",
        "author": "Karolina silva",
        "author_id": 290,
        "published": "2026-04-08T14:55:30-04:00",
        "categories": [
          "Notícias"
        ],
        "category_ids": [
          5
        ]
      }
    ],
    "afolhalivre": [],
    "omatogrossense": [
      {
        "title": "Moradores encontram homem morto dentro de terminal no CPA III em Cuiabá; veja vídeo",
        "link": "https://omatogrossense.com/homem-morto-dentro-terminal-cpa-cuiaba-video/",
        "author": "Mhylenna",
        "author_id": 16,
        "published": "2026-04-08T14:04:31-04:00",
        "categories": [
          "MT Notícias"
        ],
        "category_ids": [
          20
        ]
      },
      {
        "title": "Operação gigante atinge esquema de R$ 2 bilhões, prende 55 pessoas e derruba sites ilegais; Veja vídeo",
        "link": "https://omatogrossense.com/operacao-policial-atingiu-organizacao/",
        "author": "Karolina Coelho da Silva",
        "author_id": 22,
        "published": "2026-04-08T14:55:37-04:00",
        "categories": [
          "Brasil e Mundo"
        ],
        "category_ids": [
          973
        ]
      }
    ],
    "portalnortemt": [],
    "portalpantanalmt": [],
    "roonoticias": []
  },
  "menu_category_ids": {
    "perrenguematogrosso": [
      4,
      5,
      16,
      509,
      510
    ],
    "afolhalivre": [
      5,
      7,
      20,
      973,
      3032
    ],
    "omatogrossense": [
      5,
      7,
      20,
      973
    ],
    "portalnortemt": [
      5,
      7,
      20,
      973,
      3030
    ],
    "portalpantanalmt": [
      5,
      7,
      20,
      973,
      3105
    ],
    "roonoticias": [
      5,
      7,
      20,
      973,
      3118
    ]
  }
}